numerous/files/__init__.py
numerous/files/aws_s3.py
numerous/files/file_manager.py
numerous/files/local.py
numerous/files/memory.py
numerous/files/py.typed
numerous_files-0.1.2.dist-info/LICENSE.md
numerous_files-0.1.2.dist-info/METADATA
numerous_files-0.1.2.dist-info/WHEEL
numerous_files-0.1.2.dist-info/top_level.txt
numerous_files-0.1.2.dist-info/RECORD
