Metadata-Version: 2.1
Name: numerous-files
Version: 0.1.2
Classifier: Programming Language :: Python :: 3
License-File: LICENSE.md
Requires-Dist: boto3
Provides-Extra: dev
Requires-Dist: pytest ==8.0.2 ; extra == 'dev'
Requires-Dist: pytest-asyncio ==0.23.5 ; extra == 'dev'
Requires-Dist: pytest-cov ; extra == 'dev'
Requires-Dist: ruff ==0.4.2 ; extra == 'dev'
Requires-Dist: mypy ==1.10.0 ; extra == 'dev'
Requires-Dist: coverage ==7.4.0 ; extra == 'dev'
Requires-Dist: twine ==5.0.0 ; extra == 'dev'
Requires-Dist: pytest-env ==1.1.3 ; extra == 'dev'
Requires-Dist: pre-commit ==3.7.0 ; extra == 'dev'
Requires-Dist: mkdocs ==1.6.0 ; extra == 'dev'
Requires-Dist: mkdocstrings ==0.25.0 ; extra == 'dev'
Requires-Dist: mkdocstrings-python ==1.10.0 ; extra == 'dev'
Requires-Dist: mkdocs-snippet-plugin ==1.0.2 ; extra == 'dev'
